LICENSE
MANIFEST.in
README.md
pyproject.toml
setup.py
./slime_src/ext/main.cpp
./slime_src/ext/slime.cpp
MRPhantom.egg-info/PKG-INFO
MRPhantom.egg-info/SOURCES.txt
MRPhantom.egg-info/dependency_links.txt
MRPhantom.egg-info/requires.txt
MRPhantom.egg-info/top_level.txt
example/Example_2D.py
example/Example_3D.py
example/Example_Simple.py
example/Example_Utility.py
slime_src/Function.py
slime_src/__init__.py
slime_src/ext/main.cpp
slime_src/ext/slime.cpp
slime_src/ext/slime.h