Metadata-Version: 2.4
Name: MRPhantom
Version: 0.0.1
Summary: MRI Phantom of a Slime with Repiratory and Cardiac Motion, and M0, Phase, T1, T2, B0 maps, Boosted by a C-API Backend.
Author-email: Ryan <ryan_shanghaitech@proton.me>
License-Expression: MIT
Project-URL: Repository, https://github.com/RyanShanghaitech/Slime
Project-URL: Examples, https://github.com/RyanShanghaitech/Slime/tree/main/example
Keywords: MRI,Phantom,Motion,Quantitative
License-File: LICENSE
Requires-Dist: numpy
Dynamic: license-file
